service_now_api_sdk/__init__.py
service_now_api_sdk/exceptions.py
service_now_api_sdk/sdk/__init__.py
service_now_api_sdk/sdk/servicenow/__init__.py
service_now_api_sdk/sdk/servicenow/attachments/__init__.py
service_now_api_sdk/sdk/servicenow/attachments/client.py
service_now_api_sdk/sdk/servicenow/attachments/exceptions.py
service_now_api_sdk/sdk/servicenow/helpers/__init__.py
service_now_api_sdk/sdk/servicenow/helpers/client.py
service_now_api_sdk/sdk/servicenow/helpers/query_builder.py
service_now_api_sdk/sdk/servicenow/table/__init__.py
service_now_api_sdk/sdk/servicenow/table/client.py
service_now_api_sdk/sdk/servicenow/table/exceptions.py
service_now_api_sdk/sdk/servicenow/utils/__init__.py
service_now_api_sdk/sdk/servicenow/utils/aux_functions.py
service_now_api_sdk/sdk/servicenow/utils/constants.py
service_now_api_sdk/settings.py
service_now_api_sdk-0.0.27.dist-info/METADATA
service_now_api_sdk-0.0.27.dist-info/WHEEL
service_now_api_sdk-0.0.27.dist-info/licenses/LICENSE
service_now_api_sdk-0.0.27.dist-info/RECORD
