Metadata-Version: 2.4
Name: service_now_api_sdk
Version: 0.0.27
Summary: Service Now API SDK is used to facilitate integrations, automations and also code reuse
License: MIT
License-File: LICENSE
Author: stone_people_analytics
Author-email: systems-techpeople@stone.com.br
Maintainer: guilherme_lsilva
Maintainer-email: manager.guilherme.silva@gmail.com
Requires-Python: >=3.9,<4.0
Classifier: License :: OSI Approved :: MIT License
Classifier: Programming Language :: Python :: 3
Classifier: Programming Language :: Python :: 3.9
Classifier: Programming Language :: Python :: 3.10
Classifier: Programming Language :: Python :: 3.11
Classifier: Programming Language :: Python :: 3.12
Classifier: Programming Language :: Python :: 3.13
Classifier: Programming Language :: Python :: 3.14
Requires-Dist: requests (>=2.27.1,<3.0.0)
Project-URL: Repository, https://github.com/people-analytics-tech/service-now-api-sdk
